gapoic/__init__.py
gapoic/abs/__init__.py
gapoic/abs/doubly_linked_list.py
gapoic/abs/node.py
gapoic/app_config.py
gapoic/exceptions.py
gapoic/http/__init__.py
gapoic/http/_async.py
gapoic/http/_sync.py
gapoic/http/base.py
gapoic/lru.py
gapoic/misc.py
gapoic-0.5.1.dist-info/entry_points.txt
gapoic-0.5.1.dist-info/WHEEL
gapoic-0.5.1.dist-info/METADATA
gapoic-0.5.1.dist-info/RECORD
