Metadata-Version: 2.1
Name: gapoic
Version: 0.5.1
Summary: stuff utils
License: MIT
Author: vutr
Author-email: me@vutr.io
Requires-Python: >=3.7,<4.0
Classifier: License :: OSI Approved :: MIT License
Classifier: Programming Language :: Python :: 3
Classifier: Programming Language :: Python :: 3.7
Classifier: Programming Language :: Python :: 3.8
